robotframework_browser_translation_fi/__init__.py
robotframework_browser_translation_fi/translation.json
robotframework_browser_translation_fi-0.7.0.dist-info/LICENSE
robotframework_browser_translation_fi-0.7.0.dist-info/METADATA
robotframework_browser_translation_fi-0.7.0.dist-info/WHEEL
robotframework_browser_translation_fi-0.7.0.dist-info/top_level.txt
robotframework_browser_translation_fi-0.7.0.dist-info/RECORD
